<?xml version="1.0" encoding="UTF-8"?>
<actions>
        <action>
            <actionName>CUSTOM-cobertura</actionName>
            <displayName>cobertura</displayName>
            <goals>
                <goal>cobertura:cobertura</goal>
            </goals>
            <activatedProfiles>
                <activatedProfile>cobertura</activatedProfile>
            </activatedProfiles>
        </action>
        <pluginRepositories>
    <pluginRepository>
        <id>central</id>
        <name>Central Repository</name>
        <url>https://repo.maven.apache.org/maven2</url>
        <layout>default</layout>
        <snapshots>
            <enabled>false</enabled>
        </snapshots>
        <releases>
            <updatePolicy>never</updatePolicy>
        </releases>
    </pluginRepository>
</pluginRepositories>
<repositories>
    <repository>
        <id>central</id>
        <name>Central Repository</name>
        <url>https://repo.maven.apache.org/maven2</url>
        <layout>default</layout>
        <snapshots>
            <enabled>false</enabled>
        </snapshots>
    </repository>
</repositories>
    </actions>
